{"To the people of Las Vegas and to the families of the victims, we are with you! HASH_TAG https://t.co/cT6c5RIFcr": {"compound": -0.3182, "neg": 0.103, "neu": 0.897, "pos": 0.0, "1_gram": 1.6904150496773258, "2_gram": 2.3705208210041357, "3_gram": 2.970577331247202, "4_gram": 3.4438222472873714, "charc": 112, "wordc": 22, "excc": 1, "quesc": 0, "quotec": 0, "captc": 0}, "It was an honor to travel w/ @POTUS to Las Vegas. Prayers for the victims. Prayers for the first responders. Prayer\u2026 URL": {"compound": 0.2263, "neg": 0.094, "neu": 0.776, "pos": 0.131, "1_gram": 2.7826966161777635, "2_gram": 5.483285389218269, "3_gram": 7.733874162258774, "4_gram": 9.813034363870715, "charc": 120, "wordc": 22, "excc": 0, "quesc": 0, "quotec": 0, "captc": 1}, "Heading to Las Vegas tmrw w/ @POTUS to meet with law enforcement, first responders, and families of victims. URL": {"compound": -0.3182, "neg": 0.119, "neu": 0.881, "pos": 0.0, "1_gram": 3.4479962038124095, "2_gram": 5.876384564487561, "3_gram": 8.250985385942629, "4_gram": 10.58853646468758, "charc": 112, "wordc": 19, "excc": 0, "quesc": 0, "quotec": 0, "captc": 1}, "Our community is shaken and deeply saddened by the senseless violence against our innocent neighbors. https://t.co/wlVRMjZadR": {"compound": -0.7713, "neg": 0.357, "neu": 0.549, "pos": 0.094, "1_gram": 5.512356326614032, "2_gram": 9.992454588711933, "3_gram": 14.067790946047936, "4_gram": 18.047017463567013, "charc": 125, "wordc": 19, "excc": 0, "quesc": 0, "quotec": 0, "captc": 0}, "To the courageous first responders, THANK YOU! HASH_TAG https://t.co/82KuUNjQ5J": {"compound": 0.7096, "neg": 0.0, "neu": 0.604, "pos": 0.396, "1_gram": 2.077334968801993, "2_gram": 3.1443606592534707, "3_gram": 4.131337088621205, "4_gram": 4.574835257119373, "charc": 79, "wordc": 12, "excc": 1, "quesc": 0, "quotec": 0, "captc": 2}, "Communities across America will feel the pain of this violence personally\u2014including my home town of Bakersfield. URL": {"compound": -0.8126, "neg": 0.316, "neu": 0.684, "pos": 0.0, "1_gram": 8.235046714610608, "2_gram": 15.450485586083962, "3_gram": 21.165924457557324, "4_gram": 26.738181510848854, "charc": 116, "wordc": 18, "excc": 0, "quesc": 0, "quotec": 0, "captc": 0}, "We are so thankful for the bravery of the first responders and citizens who put themselves in danger to care for and protect others.": {"compound": 0.8845, "neg": 0.094, "neu": 0.526, "pos": 0.38, "1_gram": 7.073260790439957, "2_gram": 13.629280201569575, "3_gram": 19.646838074237643, "4_gram": 25.308840391350166, "charc": 132, "wordc": 24, "excc": 0, "quesc": 0, "quotec": 0, "captc": 0}, "Such a senseless tragedy in Las Vegas. This horrific act has our nation praying for the victims and their families. May God bless us all.": {"compound": -0.7615, "neg": 0.32, "neu": 0.482, "pos": 0.198, "1_gram": 3.9327853578781995, "2_gram": 7.288647638833322, "3_gram": 10.442128967407491, "4_gram": 13.004701205072568, "charc": 137, "wordc": 25, "excc": 0, "quesc": 0, "quotec": 0, "captc": 0}}