{"I\u2019ll keep fighting for a world where everyone feels safe to be who they are and love who they love.\u2026 https://t.co/wFGx7WBc5f": {"sentiment_analysis_weight": {"neg": 0.079, "neu": 0.566, "pos": 0.355, "compound": 0.8689}, "1_gram": 1.7838074348907078, "2_gram": 2.565665552042624, "3_gram": 3.331253197041715, "4_gram": 4.082201145454207}, "ALERT: Children\u2019s Health Insurance Program is at risk. That means 9 million children could be left uninsured.\u2026 https://t.co/jM6PSZkOcN": {"sentiment_analysis_weight": {"neg": 0.099, "neu": 0.798, "pos": 0.103, "compound": 0.0258}, "1_gram": 1.7827743472841018, "2_gram": 2.4226915517110608, "3_gram": 3.0095797209108426, "4_gram": 3.5949262593536817}, "Congress needs to step up and do its job so doctors and nurses and health centers can do theirs. https://t.co/0y1DjwsKLE": {"sentiment_analysis_weight": {"neg": 0.0, "neu": 1.0, "pos": 0.0, "compound": 0.0}, "1_gram": 2.7180054671528384, "2_gram": 4.425909924204667, "3_gram": 6.097702639262399, "4_gram": 7.768718896311602}, "Before millions are subjected to another data breach like @Equifax \u2013 we must do something about it. That\u2019s why I in\u2026 https://t.co/ZnisL3cUJr": {"sentiment_analysis_weight": {"neg": 0.0, "neu": 0.894, "pos": 0.106, "compound": 0.3612}, "1_gram": 1.8718690318348088, "2_gram": 2.7199285398600934, "3_gram": 3.5511971489826184, "4_gram": 4.3792546329471165}, "Access to birth control is about freedom &amp; the ability to plan &amp; build a future. This attack on basic health care is wrong.": {"sentiment_analysis_weight": {"neg": 0.195, "neu": 0.523, "pos": 0.282, "compound": 0.4543}, "1_gram": 0.7558628040577323, "2_gram": 1.4020764853084473, "3_gram": 2.0465806895645144, "4_gram": 2.543682296417984}, "The year is 2017, not 1917. Millions of Americans use contraception to prevent pregnancy, avoid STIs &amp; manage health conditions.": {"sentiment_analysis_weight": {"neg": 0.103, "neu": 0.845, "pos": 0.052, "compound": -0.2732}, "1_gram": 4.410548600584912, "2_gram": 8.786255118079138, "3_gram": 13.138948899517144, "4_gram": 16.490355679668152}, "Evidently the GOP believe the single most important issue facing our nation is to let employers deny women access to birth control coverage.": {"sentiment_analysis_weight": {"neg": 0.094, "neu": 0.824, "pos": 0.082, "compound": -0.079}, "1_gram": 2.229406337871559, "2_gram": 3.418812675743118, "3_gram": 4.560240641525636, "4_gram": 5.547447828087374}, "Enough is enough. The credit reporting industry is broken. I want consumers to have control of their own data \u2013 not\u2026 https://t.co/PZLAf2lm8R": {"sentiment_analysis_weight": {"neg": 0.119, "neu": 0.731, "pos": 0.15, "compound": -0.0516}, "1_gram": 1.7114977215779787, "2_gram": 2.37537639553691, "3_gram": 3.03757061192903, "4_gram": 3.6517917984012156}, "It's ok, @FoxNews! We can agree that @WellsFargo CEO should be fired. This isn't about politics. It's about protect\u2026 https://t.co/5WwKiL46kX": {"sentiment_analysis_weight": {"neg": 0.125, "neu": 0.623, "pos": 0.253, "compound": 0.4019}, "1_gram": 1.7530489649668237, "2_gram": 2.5041785441371025, "3_gram": 3.2537230185715162, "4_gram": 3.836246844038377}, "Incentives for companies like @Equifax are out of whack. Consumers should control their own data. Execs should face consequences for neglect": {"sentiment_analysis_weight": {"neg": 0.116, "neu": 0.698, "pos": 0.186, "compound": 0.2023}, "1_gram": 3.337564921174735, "2_gram": 5.3417965090161355, "3_gram": 7.344099456548953, "4_gram": 8.783902404081772}, ".@Equifax did a bad job protecting data because they had no reason to care. They\u2019re making MORE money selling fraud\u2026 https://t.co/U1g6DVMoFw": {"sentiment_analysis_weight": {"neg": 0.305, "neu": 0.594, "pos": 0.1, "compound": -0.7624}, "1_gram": 2.1253342147225753, "2_gram": 3.226278185542711, "3_gram": 4.281370154628493, "4_gram": 5.335030555206491}, "About to question the former @Equifax CEO about his company\u2019s inexcusable data breach &amp; response. Watch live: https://t.co/QGWCNeXZnq": {"sentiment_analysis_weight": {"neg": 0.0, "neu": 1.0, "pos": 0.0, "compound": 0.0}, "1_gram": 2.1470247139444396, "2_gram": 3.789775923615375, "3_gram": 5.431707201298848, "4_gram": 6.982375405772351}, "The fmr CEO of @Equifax is testifying before the @SenateBanking Committee this morning. Watch the hearing live here: https://t.co/QGWCNeXZnq": {"sentiment_analysis_weight": {"neg": 0.0, "neu": 1.0, "pos": 0.0, "compound": 0.0}, "1_gram": 1.8408829890306466, "2_gram": 3.1814066535912953, "3_gram": 4.188199528538802, "4_gram": 5.142006842238056}, ".@WellsFargo will never change if the people responsible for the fake accounts scam are still in charge. CEO Tim Sl\u2026 https://t.co/BLzO7HUttf": {"sentiment_analysis_weight": {"neg": 0.234, "neu": 0.687, "pos": 0.079, "compound": -0.6705}, "1_gram": 3.3751437599849274, "2_gram": 5.6914639905580895, "3_gram": 8.004232190718952, "4_gram": 10.300517376320865}, ".@WellsFargo CEO Tim Sloan enabled the bank\u2019s massive fake accounts scam, got rich off it, &amp; helped cover it up. He\u2026 https://t.co/tY9lqllIhb": {"sentiment_analysis_weight": {"neg": 0.217, "neu": 0.669, "pos": 0.115, "compound": -0.4939}, "1_gram": 3.3780373267376262, "2_gram": 5.697251124063487, "3_gram": 7.963435886162169, "4_gram": 9.979266665959974}, "I have more questions for @WellsFargo CEO Sloan about his plans for his lower-level employees. Watch now: https://t.co/nm6TAiiTU6": {"sentiment_analysis_weight": {"neg": 0.104, "neu": 0.896, "pos": 0.0, "compound": -0.296}, "1_gram": 1.5202242130811299, "2_gram": 2.7051657750901357, "3_gram": 3.8858784631948105, "4_gram": 5.0613352082142855}, "About to question @WellsFargo CEO Sloan about his role in the massive fake accounts scandal. Watch live now: https://t.co/nm6TAiiTU6": {"sentiment_analysis_weight": {"neg": 0.24, "neu": 0.76, "pos": 0.0, "compound": -0.7184}, "1_gram": 1.5566983453587793, "2_gram": 2.7757898531107217, "3_gram": 3.994061428875207, "4_gram": 5.1210699314297115}, "The new CEO of @WellsFargo is testifying before the @SenateBanking Committee. Watch the whole hearing live now: https://t.co/nm6TAiiTU6": {"sentiment_analysis_weight": {"neg": 0.0, "neu": 1.0, "pos": 0.0, "compound": 0.0}, "1_gram": 1.604110344980997, "2_gram": 2.874528032158665, "3_gram": 4.133437151945411, "4_gram": 5.3393607104839}, "The federal government cannot turn its back on our fellow US citizens who are stranded without food, water, electricity &amp; medicine.": {"sentiment_analysis_weight": {"neg": 0.0, "neu": 1.0, "pos": 0.0, "compound": 0.0}, "1_gram": 2.199459319729627, "2_gram": 4.0652259816559235, "3_gram": 5.892442747241097, "4_gram": 7.361326179492939}, "We are worried sick about our brothers and sisters in Puerto Rico and the US Virgin Islands. We must act NOW. https://t.co/1ESchwlqZF": {"sentiment_analysis_weight": {"neg": 0.2, "neu": 0.8, "pos": 0.0, "compound": -0.6705}, "1_gram": 2.0603040480070263, "2_gram": 3.1190813784568023, "3_gram": 4.174604109769625, "4_gram": 5.063106192114894}, "Tragedies like Las Vegas have happened too many times. We need to have the conversation about how to stop gun violence. We need it NOW.": {"sentiment_analysis_weight": {"neg": 0.34, "neu": 0.587, "pos": 0.073, "compound": -0.8442}, "1_gram": 0.8256445096639182, "2_gram": 1.395671041799746, "3_gram": 1.9515830661878097, "4_gram": 2.4747690446919344}, "Thoughts &amp; prayers are NOT enough. Not when more moms &amp; dads will bury kids this week, &amp; more sons &amp; daughters will grow up without parents.": {"sentiment_analysis_weight": {"neg": 0.0, "neu": 1.0, "pos": 0.0, "compound": 0.0}, "1_gram": 4.38557823710513, "2_gram": 8.602678213340694, "3_gram": 12.78701533027217, "4_gram": 16.92643929583889}, "I\u2019m heartsick for people in Nevada &amp; across the country who woke up to this news &amp; are worried that their family &amp; friends are ok.": {"sentiment_analysis_weight": {"neg": 0.075, "neu": 0.746, "pos": 0.18, "compound": 0.4767}, "1_gram": 2.350679409912827, "2_gram": 4.532742835420199, "3_gram": 6.701196429898384, "4_gram": 8.322030976757521}, "I\u2019m heartsick for the victims of last night\u2019s massacre in Las Vegas &amp; their loved ones.": {"sentiment_analysis_weight": {"neg": 0.12, "neu": 0.677, "pos": 0.203, "compound": 0.3818}, "1_gram": 1.7980008294783303, "2_gram": 3.5171292642947916, "3_gram": 5.166681481527444, "4_gram": 6.310351345818922}, "The definition of \"poor leadership\" is sitting at your golf club while millions of US citizens beg for your help, @realDonaldTrump.": {"sentiment_analysis_weight": {"neg": 0.125, "neu": 0.766, "pos": 0.109, "compound": -0.1027}, "1_gram": 3.131804612645774, "2_gram": 6.24539275796441, "3_gram": 8.351518216715876, "4_gram": 10.45136750628134}, "Disaster relief workers &amp; volunteers are doing God's work right now. PR needs help, not bullying, from the @POTUS. https://t.co/taJi5os93C": {"sentiment_analysis_weight": {"neg": 0.128, "neu": 0.529, "pos": 0.344, "compound": 0.7137}, "1_gram": 2.485477623509914, "2_gram": 3.9183236680724587, "3_gram": 5.310772256355193, "4_gram": 6.6758398353100175}, "PR is in CRISIS. US citizens are dying. Millions of people need their govt's help. Stop playing politics with their lives, @realDonaldTrump.": {"sentiment_analysis_weight": {"neg": 0.219, "neu": 0.625, "pos": 0.156, "compound": -0.4215}, "1_gram": 0.7676119589653532, "2_gram": 1.4647351961261952, "3_gram": 2.129321432000035, "4_gram": 2.787126034357159}, "FEMA's Puerto Rico plans are outdated &amp; are outpaced by charities. Distribution is woefully inadequate &amp; people need basic medical care now.": {"sentiment_analysis_weight": {"neg": 0.181, "neu": 0.604, "pos": 0.215, "compound": 0.25}, "1_gram": 4.817335570284867, "2_gram": 9.601275385263866, "3_gram": 14.379482097241356, "4_gram": 19.070349065629113}, "I just got off the phone with Mayor @CarmenYulinCruz. I told her to keep up her heroic work &amp; leadership on behalf of Puerto Rico.": {"sentiment_analysis_weight": {"neg": 0.0, "neu": 0.859, "pos": 0.141, "compound": 0.5574}, "1_gram": 2.172045820916649, "2_gram": 4.331153313105498, "3_gram": 6.470753229536774, "4_gram": 8.573827171942067}, ".@realDonaldTrump should use his authority to more quickly &amp; comprehensively respond to Puerto Rico &amp; the USVI. The\u2026 https://t.co/e4RcJMKyXI": {"sentiment_analysis_weight": {"neg": 0.0, "neu": 0.939, "pos": 0.061, "compound": 0.0772}, "1_gram": 2.6487908729665666, "2_gram": 4.279724603075989, "3_gram": 5.90219636077657, "4_gram": 7.474314136176268}, "Congress must immediately take up an appropriations bill to come to Puerto Rico &amp; the US Virgin Islands\u2019 aid.": {"sentiment_analysis_weight": {"neg": 0.0, "neu": 1.0, "pos": 0.0, "compound": 0.0}, "1_gram": 0.6646878916474586, "2_gram": 1.2716557255748588, "3_gram": 1.7897346706133712, "4_gram": 2.0880333958716633}, "Today I met with community leaders &amp; local officials in Worcester &amp; Springfield, &amp; listened to family of people str\u2026 https://t.co/cSngRNCnOi": {"sentiment_analysis_weight": {"neg": 0.0, "neu": 1.0, "pos": 0.0, "compound": 0.0}, "1_gram": 4.36201154180924, "2_gram": 7.719456873572817, "3_gram": 11.0745554313178, "4_gram": 14.357871435333323}, "Every day, I get more &amp; more calls from people across MA who are desperately worried about the people they love in Puerto Rico.": {"sentiment_analysis_weight": {"neg": 0.166, "neu": 0.69, "pos": 0.145, "compound": 0.1027}, "1_gram": 0.8895203301850124, "2_gram": 1.7548937546441723, "3_gram": 2.5961518822996767, "4_gram": 3.4345614116408516}, "With every day that passes, I\u2019m more outraged that the federal govt isn\u2019t doing more to help our fellow Americans in Puerto Rico &amp; the USVI.": {"sentiment_analysis_weight": {"neg": 0.127, "neu": 0.773, "pos": 0.1, "compound": -0.2058}, "1_gram": 0.6975813592114534, "2_gram": 1.3370819103420992, "3_gram": 1.9630652422659056, "4_gram": 2.573837084748642}, "Puerto Rico was already suffering from an economic crisis long before it got hit by the hurricane. Now it faces another humanitarian crisis.": {"sentiment_analysis_weight": {"neg": 0.361, "neu": 0.639, "pos": 0.0, "compound": -0.9062}, "1_gram": 1.277954396321552, "2_gram": 2.5070305875148984, "3_gram": 3.5822606248620907, "4_gram": 4.628648256077025}, ".@realDonaldTrump should pick a new @HHSGov Sec who cares less about luxury travel &amp; ripping away health care &amp; more about families' health.": {"sentiment_analysis_weight": {"neg": 0.0, "neu": 0.763, "pos": 0.237, "compound": 0.7351}, "1_gram": 3.2194023109341527, "2_gram": 6.416116561136767, "3_gram": 9.594865305111332, "4_gram": 12.60267387814573}, "The Janus case could tilt the playing field further in favor of corporations &amp; make it much harder for workers to stand up for themselves.": {"sentiment_analysis_weight": {"neg": 0.0, "neu": 0.836, "pos": 0.164, "compound": 0.5423}, "1_gram": 2.324898483034513, "2_gram": 4.5244376415990315, "3_gram": 6.223012480009256, "4_gram": 7.804024594405145}, "In deciding to take up the Janus case, the GOP-appointed SCOTUS majority is poised to deal the knock-out blow to public sector unions.": {"sentiment_analysis_weight": {"neg": 0.0, "neu": 0.923, "pos": 0.077, "compound": 0.25}, "1_gram": 5.10206683665596, "2_gram": 10.07823439273638, "3_gram": 14.221068615483471, "4_gram": 18.313480362522913}, "When the GOP stole @BarackObama's SCOTUS seat &amp; forced Gorsuch through the Senate, they knew their investment would pay off. Today it has.": {"sentiment_analysis_weight": {"neg": 0.173, "neu": 0.827, "pos": 0.0, "compound": -0.5267}, "1_gram": 3.864817181721059, "2_gram": 7.710893733756959, "3_gram": 11.554691575526325, "4_gram": 15.382559570886386}, "Powerful interests invested vast sums of money into confirming judges who will tilt our courts in favor of billionaires &amp; big businesses.": {"sentiment_analysis_weight": {"neg": 0.0, "neu": 0.717, "pos": 0.283, "compound": 0.7579}, "1_gram": 3.8294253536602296, "2_gram": 7.487422135891887, "3_gram": 10.963367636072267, "4_gram": 13.93780027694856}, "RT @EMKInstitute: #OTD in 2015 @SenWarren was at the Institute for a #GettingToThePoint convo on equality. See the program: https://t.co/kB\u2026": {"sentiment_analysis_weight": {"neg": 0.0, "neu": 1.0, "pos": 0.0, "compound": 0.0}, "1_gram": 4.917630411435375, "2_gram": 8.834068927757517, "3_gram": 11.750109987799858, "4_gram": 14.16579706554131}, "#NotOnePenny in tax cuts for the wealthy &amp; giant corporations \u2013 especially not on the backs of everyone else. We'll fight this GOP tax plan.": {"sentiment_analysis_weight": {"neg": 0.163, "neu": 0.713, "pos": 0.124, "compound": -0.2851}, "1_gram": 1.0831990993600455, "2_gram": 1.9555286335026998, "3_gram": 2.8223077242791152, "4_gram": 3.673072015901196}, "And the GOP tax plan will explode the deficit, which will lead the GOP to say we need to gut Medicaid, Medicare, infrastructure &amp; education.": {"sentiment_analysis_weight": {"neg": 0.101, "neu": 0.899, "pos": 0.0, "compound": -0.4019}, "1_gram": 1.7870224783174933, "2_gram": 3.5315056896192796, "3_gram": 5.274116717146985, "4_gram": 6.942864108311052}, "The GOP plan gets rid of the state/local tax deduction for working families while repealing the estate tax for a handful of rich families.": {"sentiment_analysis_weight": {"neg": 0.0, "neu": 0.865, "pos": 0.135, "compound": 0.5574}, "1_gram": 1.7208523490064938, "2_gram": 3.4314443834439814, "3_gram": 5.0806727815178325, "4_gram": 6.718219926062604}, "While the GOP plan slashes the income tax rate for the highest earners, it increases the tax rate that applies to many working families.": {"sentiment_analysis_weight": {"neg": 0.073, "neu": 0.927, "pos": 0.0, "compound": -0.2023}, "1_gram": 2.270954376214218, "2_gram": 4.490341095662759, "3_gram": 6.698615802469261, "4_gram": 8.879397840654057}, "The GOP tax plan delivers massive tax cuts to millionaires &amp; giant corporations &amp; kicks working families to the curb.": {"sentiment_analysis_weight": {"neg": 0.104, "neu": 0.896, "pos": 0.0, "compound": -0.296}, "1_gram": 2.268298992233189, "2_gram": 3.536238659996382, "3_gram": 4.792455366925943, "4_gram": 6.043598435357158}, "The \u201cnew\u201d Republican tax plan is the same warmed-over, trickle-down plan they\u2019ve been pushing for decades.": {"sentiment_analysis_weight": {"neg": 0.0, "neu": 0.896, "pos": 0.104, "compound": 0.2732}, "1_gram": 1.8338351497279188, "2_gram": 3.524453832128698, "3_gram": 5.202997083264078, "4_gram": 6.6916178537793}, "The people of Puerto Rico &amp; the USVI need to know their federal government hasn't forgotten them and is doing everything it can to aid them.": {"sentiment_analysis_weight": {"neg": 0.071, "neu": 0.929, "pos": 0.0, "compound": -0.2263}, "1_gram": 0.6795206949661927, "2_gram": 1.3417329129200164, "3_gram": 1.9520525789812881, "4_gram": 2.5611380810232216}, "Today I joined fellow Democratic senators in calling for an appropriations bill immediately to help the people of P\u2026 https://t.co/MjIULwXgHN": {"sentiment_analysis_weight": {"neg": 0.0, "neu": 0.876, "pos": 0.124, "compound": 0.4019}, "1_gram": 1.8006398130569956, "2_gram": 2.5967134160683285, "3_gram": 3.3904402450610616, "4_gram": 4.100479758419576}, "Millions of Americans live on Puerto Rico &amp; the USVI. They'll need huge immediate &amp; long-term aid \u2013 far more than they've received so far.": {"sentiment_analysis_weight": {"neg": 0.0, "neu": 0.919, "pos": 0.081, "compound": 0.3182}, "1_gram": 0.8892656607953728, "2_gram": 1.7095063000204265, "3_gram": 2.519226513069714, "4_gram": 3.197453219625495}, "In the wake of powerful hurricanes, Puerto Rico &amp; the US Virgin Islands face an urgent humanitarian crisis. Congress must address it NOW.": {"sentiment_analysis_weight": {"neg": 0.143, "neu": 0.697, "pos": 0.16, "compound": -0.128}, "1_gram": 1.183198617710432, "2_gram": 2.359879977317233, "3_gram": 3.534282626657494, "4_gram": 4.468685275997757}, ".@SenateGOP withdrew their latest health care repeal bill because they didn\u2019t have the votes. I have two words for\u2026 https://t.co/YdsmlTSQwW": {"sentiment_analysis_weight": {"neg": 0.0, "neu": 0.862, "pos": 0.138, "compound": 0.4939}, "1_gram": 2.443219423555084, "2_gram": 3.8464388471101687, "3_gram": 4.249260814385444, "4_gram": 4.645846446418657}, ".@realDonaldTrump isn't following through on his promise to fix NAFTA and boost working families. It's time for Congress to take action.": {"sentiment_analysis_weight": {"neg": 0.0, "neu": 0.792, "pos": 0.208, "compound": 0.6124}, "1_gram": 0.8027214191314974, "2_gram": 1.554252362072519, "3_gram": 2.245664257394492, "4_gram": 2.936299694707934}, "I also wrote a bill w/ @SenSherrodBrown &amp; @SenGillibrand to stop states from restricting workers' right to unionize. https://t.co/DdOxn2HdKp": {"sentiment_analysis_weight": {"neg": 0.231, "neu": 0.769, "pos": 0.0, "compound": -0.5859}, "1_gram": 3.8686019641749563, "2_gram": 6.735254610611121, "3_gram": 9.561509800767478, "4_gram": 12.220744341956282}, "I wrote to the Admin demanding the removal of ISDS from NAFTA. We should look out for families \u2013 not corporations. https://t.co/NVJNOV64uO": {"sentiment_analysis_weight": {"neg": 0.083, "neu": 0.917, "pos": 0.0, "compound": -0.2263}, "1_gram": 2.8460406583283606, "2_gram": 4.690131998917931, "3_gram": 6.367159216561019, "4_gram": 8.043409976195578}, "Now @realDonaldTrump &amp; his Administration are reportedly proposing NAFTA provisions that do nothing to bring back American jobs.": {"sentiment_analysis_weight": {"neg": 0.0, "neu": 1.0, "pos": 0.0, "compound": 0.0}, "1_gram": 1.5012327476409946, "2_gram": 2.9611332320396144, "3_gram": 4.395600816005331, "4_gram": 5.819121578402817}, "The Trump Administration has failed to get rid of ISDS - the corporate courts in NAFTA that give big businesses their own special rights.": {"sentiment_analysis_weight": {"neg": 0.122, "neu": 0.778, "pos": 0.1, "compound": -0.1531}, "1_gram": 1.2490284090444204, "2_gram": 2.4576974936188436, "3_gram": 3.559830630480851, "4_gram": 4.5810113863904744}, "Despite promising to fix NAFTA's problems, @realDonaldTrump &amp; his Admin have failed to fight for workers through the first 3 rounds.": {"sentiment_analysis_weight": {"neg": 0.404, "neu": 0.596, "pos": 0.0, "compound": -0.8707}, "1_gram": 2.2150557875948316, "2_gram": 3.263444908522996, "3_gram": 3.7885782154976737, "4_gram": 4.29977553325119}, "The fundamental problem with NAFTA is simple: the agreement doesn't work for American workers.": {"sentiment_analysis_weight": {"neg": 0.151, "neu": 0.67, "pos": 0.179, "compound": 0.128}, "1_gram": 0.7543546274564201, "2_gram": 1.4813229034158168, "3_gram": 1.867382088466122, "4_gram": 2.1936534239503733}, "The American public deserve answers about what went wrong at @Equifax and what the company plans to do going forward.": {"sentiment_analysis_weight": {"neg": 0.14, "neu": 0.86, "pos": 0.0, "compound": -0.4767}, "1_gram": 0.7763308898680734, "2_gram": 1.5106357885994837, "3_gram": 2.209587151977359, "4_gram": 2.8502051820219014}, "Former @Equifax CEO Smith, along with the new Chair &amp; interim CEO, should all testify before the Senate Banking Committee.": {"sentiment_analysis_weight": {"neg": 0.0, "neu": 1.0, "pos": 0.0, "compound": 0.0}, "1_gram": 3.5570873900190785, "2_gram": 6.988684583959726, "3_gram": 9.395891533997933, "4_gram": 11.74322052827718}, "It\u2019s also not real accountability if the guy @Equifax promoted to Chair is a board member who served on the data security committee.": {"sentiment_analysis_weight": {"neg": 0.0, "neu": 0.794, "pos": 0.206, "compound": 0.6369}, "1_gram": 1.992417505985516, "2_gram": 3.9240920967627213, "3_gram": 5.814579039083871, "4_gram": 7.615065981405021}, "It's not real accountability if the @Equifax Chairman &amp; CEO resigns without giving back a nickel in pay or publicly answering questions.": {"sentiment_analysis_weight": {"neg": 0.242, "neu": 0.758, "pos": 0.0, "compound": -0.577}, "1_gram": 2.0773635805711788, "2_gram": 4.052807775345814, "3_gram": 5.693730988331056, "4_gram": 6.9969155816393505}, "I\u2019ve called for @Equifax execs to be held accountable for their role in failing to stop the data breach &amp; hiding it for 40 days.": {"sentiment_analysis_weight": {"neg": 0.259, "neu": 0.741, "pos": 0.0, "compound": -0.7717}, "1_gram": 2.6662191107362614, "2_gram": 5.271665374321968, "3_gram": 7.663027130865418, "4_gram": 10.003424567254575}, "Red alert: this vote could happen as soon as tomorrow. https://t.co/jFk1IL6j0d": {"sentiment_analysis_weight": {"neg": 0.0, "neu": 0.845, "pos": 0.155, "compound": 0.296}, "1_gram": 1.546416310244093, "2_gram": 1.992832620488186, "3_gram": 2.2959943315953275, "4_gram": 2.596609077945444}, "The @SenateGOP hope you won't notice when they vote to take away your legal right to take big banks to court. This\u2026 https://t.co/2JvizXR0zN": {"sentiment_analysis_weight": {"neg": 0.0, "neu": 0.731, "pos": 0.269, "compound": 0.7964}, "1_gram": 2.1143956814736673, "2_gram": 3.2284320384773393, "3_gram": 4.302070939201203, "4_gram": 5.331877596754613}, "Heading to the Senate floor now to tell the @SenateGOP: Stop fighting for the powerful interests &amp; do your job: https://t.co/jc1R7Es8hG": {"sentiment_analysis_weight": {"neg": 0.165, "neu": 0.667, "pos": 0.168, "compound": 0.0258}, "1_gram": 0.7588295653687325, "2_gram": 1.226750039828374, "3_gram": 1.69385058230056, "4_gram": 2.1602378180018644}, "The @SenateGOP are also on the verge of reversing a @CFPB rule that helps you hold firms like @WellsFargo &amp; @Equifax accountable in court.": {"sentiment_analysis_weight": {"neg": 0.0, "neu": 0.805, "pos": 0.195, "compound": 0.6249}, "1_gram": 2.5608962590936897, "2_gram": 5.077954932847816, "3_gram": 7.554114326026403, "4_gram": 9.884559433490695}, "9/30 is the deadline for funding CHIP, community health centers, Medicare programs, Medicaid payments, &amp; more. They\u2019re waiting for a vote.": {"sentiment_analysis_weight": {"neg": 0.0, "neu": 1.0, "pos": 0.0, "compound": 0.0}, "1_gram": 1.3220049796934041, "2_gram": 2.6130246257780483, "3_gram": 3.85534763803675, "4_gram": 5.095419328854159}, "The @SenateGOP have tried to manufacture a health care crisis to justify repealing the ACA, but a real crisis is about to unfold.": {"sentiment_analysis_weight": {"neg": 0.29, "neu": 0.636, "pos": 0.074, "compound": -0.7964}, "1_gram": 2.9813456778403182, "2_gram": 4.9623320312106385, "3_gram": 6.9028959088733135, "4_gram": 8.835354864637965}, "I\u2019m joining the @IndivisibleTeam live now to talk about why we must #killthebill &amp; save Americans\u2019 health care. Wat\u2026 https://t.co/99ZiqTnkx1": {"sentiment_analysis_weight": {"neg": 0.0, "neu": 0.748, "pos": 0.252, "compound": 0.7506}, "1_gram": 3.709888818532797, "2_gram": 6.4178283193268015, "3_gram": 9.114617675668958, "4_gram": 11.758421470762858}, "A man who spent 40 yrs union busting has no business on the @NLRB. Heading to the floor to oppose William Emanuel: https://t.co/jc1R7Es8hG": {"sentiment_analysis_weight": {"neg": 0.087, "neu": 0.913, "pos": 0.0, "compound": -0.296}, "1_gram": 4.363174347359522, "2_gram": 8.52527110851215, "3_gram": 12.63141485782941, "4_gram": 16.732700120341274}, "If Congress won't stand up for workers, the very least we can do is give these workers a chance to join together &amp; stand up for themselves.": {"sentiment_analysis_weight": {"neg": 0.0, "neu": 0.744, "pos": 0.256, "compound": 0.7845}, "1_gram": 0.6077414201436662, "2_gram": 1.0830754328799252, "3_gram": 1.5473441153608813, "4_gram": 1.9765897563671835}, ".@SenateGOP: before you vote to repeal the Affordable Care Act next week, listen to the doctors in your state beggi\u2026 https://t.co/Nx4g16KxxV": {"sentiment_analysis_weight": {"neg": 0.0, "neu": 0.873, "pos": 0.127, "compound": 0.4939}, "1_gram": 2.4527426642320105, "2_gram": 3.865485328464021, "3_gram": 5.254021012606698, "4_gram": 6.639924810120472}, "We must keep the pressure on to make sure this disaster of a bill isn\u2019t passed next week. https://t.co/OO21dxAOD1": {"sentiment_analysis_weight": {"neg": 0.268, "neu": 0.645, "pos": 0.087, "compound": -0.698}, "1_gram": 1.4806416717293966, "2_gram": 1.9597566259015409, "3_gram": 2.432918568238321, "4_gram": 2.8914408139885017}, "The fight to protect Medicaid and the Affordable Care Act is a fight for life and death for people who need opioid\u2026 https://t.co/tFUAZ9Tkod": {"sentiment_analysis_weight": {"neg": 0.268, "neu": 0.56, "pos": 0.171, "compound": -0.5106}, "1_gram": 1.4181694237252591, "2_gram": 1.835979522980522, "3_gram": 2.241627460073622, "4_gram": 2.6464989391581906}, "The federal government must move quickly &amp; do whatever is needed to help Puerto Rico &amp; the US Virgin Islands recover from Maria &amp; Irma.": {"sentiment_analysis_weight": {"neg": 0.0, "neu": 0.899, "pos": 0.101, "compound": 0.4019}, "1_gram": 1.0923027509135665, "2_gram": 2.14257951069047, "3_gram": 3.1543063741262514, "4_gram": 4.069604666133464}, "My thoughts are with the millions of Americans in Puerto Rico &amp; the US Virgin Islands. I hope electricity and safety are restored quickly.": {"sentiment_analysis_weight": {"neg": 0.0, "neu": 0.712, "pos": 0.288, "compound": 0.7964}, "1_gram": 1.2968358325526912, "2_gram": 2.506171665105383, "3_gram": 3.1720292367885077, "4_gram": 3.832172522757348}, "I stand with @SenFranken in saying no: We won\u2019t let Trump &amp; the GOP bypass the process &amp; stack courts with pro-corporate, right-wing judges.": {"sentiment_analysis_weight": {"neg": 0.076, "neu": 0.796, "pos": 0.128, "compound": 0.3612}, "1_gram": 3.459108247675305, "2_gram": 6.716267177611815, "3_gram": 9.708500734414, "4_gram": 12.68877507642678}, "Even worse, Trump &amp; the GOP want Dems to blue slip (aka rubber-stamp) their pro-corporate, right-wing nominees to advance. It\u2019s insulting.": {"sentiment_analysis_weight": {"neg": 0.22, "neu": 0.734, "pos": 0.045, "compound": -0.7184}, "1_gram": 5.662499942183231, "2_gram": 10.789285598652178, "3_gram": 15.843455035236495, "4_gram": 20.889169138311857}, "Trump &amp; the @SenateGOP\u2019s latest trick: flout the precedent of consulting home-state senators on nominees to serve on courts in their states.": {"sentiment_analysis_weight": {"neg": 0.052, "neu": 0.948, "pos": 0.0, "compound": -0.0516}, "1_gram": 4.0449370797023, "2_gram": 8.053926446986301, "3_gram": 12.055520602025032, "4_gram": 16.055856152018237}, "But @realDonaldTrump &amp; his GOP allies are using every tool they can to tilt our courts in favor of the wealthy &amp; well-connected.": {"sentiment_analysis_weight": {"neg": 0.0, "neu": 0.69, "pos": 0.31, "compound": 0.8573}, "1_gram": 2.9108596301045173, "2_gram": 4.813654744080003, "3_gram": 6.666334650682214, "4_gram": 8.515988838676257}, "The judges who sit on our courts should have one mission: to provide equal justice under law.": {"sentiment_analysis_weight": {"neg": 0.0, "neu": 0.825, "pos": 0.175, "compound": 0.5267}, "1_gram": 0.850650451791521, "2_gram": 1.673914552086018, "3_gram": 2.264920587864386, "4_gram": 2.8014221191382513}, "@Equifax @WellsFargo Corporate executives need to know they\u2019ll be held personally accountable just like anybody els\u2026 https://t.co/ZcFR0oy1sx": {"sentiment_analysis_weight": {"neg": 0.0, "neu": 0.884, "pos": 0.116, "compound": 0.3612}, "1_gram": 4.377297525605816, "2_gram": 7.730204807309189, "3_gram": 11.023891103320997, "4_gram": 14.240300340108844}, "With the @Equifax breach, I\u2019ll be pushing for the same type of corporate accountability that I sought in the\u2026 https://t.co/Sqi4xWDo4f": {"sentiment_analysis_weight": {"neg": 0.0, "neu": 1.0, "pos": 0.0, "compound": 0.0}, "1_gram": 3.0681603817493475, "2_gram": 5.1337955109734414, "3_gram": 7.19867385944773, "4_gram": 9.238807981718706}, "@WellsFargo But I'm still fighting for accountability at @WellsFargo. I'm pushing the Fed to remove all the Board M\u2026 https://t.co/O08puTQ43l": {"sentiment_analysis_weight": {"neg": 0.153, "neu": 0.847, "pos": 0.0, "compound": -0.5023}, "1_gram": 1.9127795118005966, "2_gram": 2.7667354941894287, "3_gram": 3.6122295041694183, "4_gram": 4.455420214109733}, "A year ago today, I told the then-CEO of @WellsFargo he should resign after the bank's massive fake accounts scam.\u2026 https://t.co/03CJdBUKVV": {"sentiment_analysis_weight": {"neg": 0.326, "neu": 0.674, "pos": 0.0, "compound": -0.8481}, "1_gram": 2.667161082679585, "2_gram": 4.333244579152275, "3_gram": 5.980748801163333, "4_gram": 7.572343485317952}, "I\u2019m doing everything I can to fight back against the Graham-Cassidy \"health care\" bill \u2013 but we need lots of people speaking up again.": {"sentiment_analysis_weight": {"neg": 0.075, "neu": 0.837, "pos": 0.088, "compound": 0.0772}, "1_gram": 0.47803472528178853, "2_gram": 0.9263423550470077, "3_gram": 1.3574456837369573, "4_gram": 1.7181786420565373}, "I told MGH Chelsea: The @SenateGOP Graham-Cassidy \u201chealth care\u201d bill is just the same set of terrible policies with\u2026 https://t.co/abSYwwHFqi": {"sentiment_analysis_weight": {"neg": 0.118, "neu": 0.76, "pos": 0.122, "compound": 0.0258}, "1_gram": 2.66127776813025, "2_gram": 4.320606218521708, "3_gram": 5.8795372126333545, "4_gram": 6.9381142244441145}, "MGH Chelsea keeps families healthy &amp; strengthens our community. They know what repealing the ACA &amp; gutting Medicaid\u2026 https://t.co/dyQtyI16fZ": {"sentiment_analysis_weight": {"neg": 0.0, "neu": 0.769, "pos": 0.231, "compound": 0.6908}, "1_gram": 3.2920927534378635, "2_gram": 5.084185506875724, "3_gram": 6.375880804033777, "4_gram": 7.590299041967869}, "@Equifax The credit reporting industry is broken and has been taking advantage of consumers for years. Time to do something about it.": {"sentiment_analysis_weight": {"neg": 0.116, "neu": 0.712, "pos": 0.172, "compound": 0.128}, "1_gram": 1.1526331615776189, "2_gram": 2.2789566934562533, "3_gram": 3.4006473965913875, "4_gram": 4.368929008817433}, "The @Equifax hack is a nightmare. I introduced the FREE Act to give consumers back control of their data. Congress\u2026 https://t.co/8urkIAHpVo": {"sentiment_analysis_weight": {"neg": 0.0, "neu": 0.858, "pos": 0.142, "compound": 0.5106}, "1_gram": 2.9011705867437243, "2_gram": 4.8019818490174515, "3_gram": 6.678005411108927, "4_gram": 8.05367499089952}, "RT @GinnieMaeGov: Thanks @SenWarren for support &amp; leadership on this issue\n\nGinnie Mae Task Force to Crack Down on some VA Lenders https://\u2026": {"sentiment_analysis_weight": {"neg": 0.0, "neu": 0.789, "pos": 0.211, "compound": 0.6808}, "1_gram": 5.148473764833048, "2_gram": 10.295371757393555, "3_gram": 13.94226974995406, "4_gram": 17.497093150439973}, "Heading to the floor to discuss the @Equifax breach. People are right to be outraged. https://t.co/jc1R7Es8hG": {"sentiment_analysis_weight": {"neg": 0.171, "neu": 0.829, "pos": 0.0, "compound": -0.5423}, "1_gram": 0.6886475096865439, "2_gram": 1.0863859284639965, "3_gram": 1.4833044152539938, "4_gram": 1.8795095952731093}, "RED ALERT: Trumpcare is not dead. https://t.co/MPsQn1hP65": {"sentiment_analysis_weight": {"neg": 0.0, "neu": 0.554, "pos": 0.446, "compound": 0.685}, "1_gram": 1.5148362613792747, "2_gram": 1.9296725227585494, "3_gram": 2.201254185000872, "4_gram": 2.457330349790795}, "@SenateGOP Tonight I\u2019m joining @SenateDems on the floor to fight (again) to save Americans\u2019 health care. Watch live\u2026 https://t.co/ORPlAGP0T6": {"sentiment_analysis_weight": {"neg": 0.1, "neu": 0.654, "pos": 0.246, "compound": 0.5859}, "1_gram": 1.3836220611148784, "2_gram": 1.727244122229757, "3_gram": 2.0482465048426035, "4_gram": 2.366945587415775}, "Cassidy-Graham is just another version of the same old heartless \u201chealth care\u201d plan the @SenateGOP have tried to jam down our throats.": {"sentiment_analysis_weight": {"neg": 0.117, "neu": 0.766, "pos": 0.117, "compound": 0.0}, "1_gram": 3.009243539310761, "2_gram": 5.00062993576438, "3_gram": 6.972523154830081, "4_gram": 8.921390242174}, "Happy Birthday, @usairforce! Happy to celebrate last week by speaking with Senior Airman Schultz of Springfield, no\u2026 https://t.co/5Jo1rsrI4X": {"sentiment_analysis_weight": {"neg": 0.075, "neu": 0.546, "pos": 0.379, "compound": 0.872}, "1_gram": 4.1825788896658205, "2_gram": 7.341901965378152, "3_gram": 10.438327584810681, "4_gram": 13.391542079085179}, "RT @TheKingCenter: This should not be about one party winning, but about doing what's just and humane. About caring for people. #GrahamCass\u2026": {"sentiment_analysis_weight": {"neg": 0.0, "neu": 0.695, "pos": 0.305, "compound": 0.81}, "1_gram": 2.9311908902547357, "2_gram": 4.861189885396242, "3_gram": 5.786915376264243, "4_gram": 6.709483564521812}, "My thoughts are with the Marseille acid attack victims, reportedly BC students. My office has reached out to BC to help however we can.": {"sentiment_analysis_weight": {"neg": 0.183, "neu": 0.678, "pos": 0.139, "compound": -0.3182}, "1_gram": 3.7740094379630613, "2_gram": 7.538475865173433, "3_gram": 11.257937313956976, "4_gram": 14.641208286550052}, "The fight to save heath care isn't over. Sound the alarm. We need you to fight today &amp; every day until this @SenateGOP bill is dead.": {"sentiment_analysis_weight": {"neg": 0.311, "neu": 0.522, "pos": 0.167, "compound": -0.6705}, "1_gram": 2.524752177187508, "2_gram": 4.799145029905019, "3_gram": 7.0604861754531765, "4_gram": 9.315690559579387}, "Let me repeat: The Graham-Cassidy @SenateGOP \"health care\" bill IS Trumpcare, &amp; it will rip health care away from millions of Americans.": {"sentiment_analysis_weight": {"neg": 0.0, "neu": 0.766, "pos": 0.234, "compound": 0.7506}, "1_gram": 0.6320579671128163, "2_gram": 1.244635414745114, "3_gram": 1.8412496589142084, "4_gram": 2.171470460460349}, "Coverage ripped away from tens of millions of Americans with Graham-Cassidy \u2013 kids with disabilities, grandparents in nursing homes.": {"sentiment_analysis_weight": {"neg": 0.0, "neu": 1.0, "pos": 0.0, "compound": 0.0}, "1_gram": 3.279495888883066, "2_gram": 6.352325111099464, "3_gram": 8.258487666649195, "4_gram": 10.128036655909101}, "Graham-Cassidy completely eliminates help for families to buy health insurance. Gone. Good luck on your own.": {"sentiment_analysis_weight": {"neg": 0.0, "neu": 0.612, "pos": 0.388, "compound": 0.835}, "1_gram": 2.1220640200204675, "2_gram": 4.178965132772766, "3_gram": 6.212544621793604, "4_gram": 7.911333051533586}, "The @SenateGOP Graham-Cassidy \"health care\" bill cuts Medicaid funding &amp; rolls back protections for people with pre-existing conditions.": {"sentiment_analysis_weight": {"neg": 0.094, "neu": 0.769, "pos": 0.137, "compound": 0.25}, "1_gram": 0.6464588305499128, "2_gram": 1.2580755780091404, "3_gram": 1.793978039754082, "4_gram": 2.2752996048128638}, "There's nothing new &amp; improved about the Graham-Cassidy bill \u2013 it's the same cruel @SenateGOP \"health care\" bill, but on steroids.": {"sentiment_analysis_weight": {"neg": 0.172, "neu": 0.741, "pos": 0.087, "compound": -0.2679}, "1_gram": 2.342100460541187, "2_gram": 3.6721527283112883, "3_gram": 4.999559621677811, "4_gram": 6.252235332248628}, "The @SenateGOP have a big 9/30 deadline to repeal the Affordable Care Act. And here's the scary thing: they might have the votes to do it.": {"sentiment_analysis_weight": {"neg": 0.109, "neu": 0.782, "pos": 0.109, "compound": 0.0}, "1_gram": 1.663027258471615, "2_gram": 3.3237758066766885, "3_gram": 4.936191021548427, "4_gram": 6.544352343087999}, "The Boston Harbor Dredging Project will create jobs, improve the passage of goods, &amp; improve Boston's long-term eco\u2026 https://t.co/1hsZc72ek0": {"sentiment_analysis_weight": {"neg": 0.0, "neu": 0.706, "pos": 0.294, "compound": 0.7845}, "1_gram": 4.218205932727411, "2_gram": 7.436052540984821, "3_gram": 10.542390581851318, "4_gram": 13.315041307083597}, "I was happy to join today's kickoff celebration of the Boston Harbor Dredging Project \u2013 deepening the harbor to all\u2026 https://t.co/24niuQca9E": {"sentiment_analysis_weight": {"neg": 0.0, "neu": 0.763, "pos": 0.237, "compound": 0.7096}, "1_gram": 4.232971286252225, "2_gram": 7.463993254765657, "3_gram": 10.689031174820512, "4_gram": 13.89045929862099}, "The Port of Boston has been vital to our economy since the colonial era. But we need to keep investing in infrastru\u2026 https://t.co/5RtG0bVopz": {"sentiment_analysis_weight": {"neg": 0.0, "neu": 0.938, "pos": 0.062, "compound": 0.1531}, "1_gram": 4.364900920197893, "2_gram": 7.729442515925791, "3_gram": 10.926919988707215, "4_gram": 14.123231790876066}, "This is good news. At least for now, @realDonaldTrump &amp; AG Sessions can\u2019t bludgeon towns into complying with dumb &amp;\u2026 https://t.co/CiPYi48yZC": {"sentiment_analysis_weight": {"neg": 0.121, "neu": 0.772, "pos": 0.107, "compound": -0.1027}, "1_gram": 5.007787124040791, "2_gram": 9.013381265625444, "3_gram": 13.017290949643284, "4_gram": 17.006353897737057}, ".@AnthemInc's decision is great \u2013 but insurers making huge profits off taxpayers shouldn\u2019t need to be shamed into providing coverage.": {"sentiment_analysis_weight": {"neg": 0.168, "neu": 0.513, "pos": 0.32, "compound": 0.5346}, "1_gram": 1.9974362335239666, "2_gram": 3.8120153241907895, "3_gram": 5.525406766401556, "4_gram": 7.158388851887178}, "Today, @AnthemInc sheepishly announced that they\u2019re partially reversing their decision to leave VA. https://t.co/PBdBMxFub0": {"sentiment_analysis_weight": {"neg": 0.07, "neu": 0.93, "pos": 0.0, "compound": -0.0516}, "1_gram": 4.014907314697149, "2_gram": 7.0252484193486335, "3_gram": 9.89233492486317, "4_gram": 11.759067448076816}, "Yesterday, I called out @AnthemInc for abandoning people in states because Congress won\u2019t help them to squeeze huge\u2026 https://t.co/53cgteYDFT": {"sentiment_analysis_weight": {"neg": 0.095, "neu": 0.586, "pos": 0.319, "compound": 0.7269}, "1_gram": 2.9451651266811942, "2_gram": 4.8580721888462595, "3_gram": 6.768632476992722, "4_gram": 8.6288387828383}, "I\u2019m glad the Senate passed our bipartisan Jobs for Heroes Act yesterday. I hope the House will pass it soon. https://t.co/3TNSO1Q9cM": {"sentiment_analysis_weight": {"neg": 0.0, "neu": 0.662, "pos": 0.338, "compound": 0.8481}, "1_gram": 1.4920551638863389, "2_gram": 1.9821610100338865, "3_gram": 2.4611167117295816, "4_gram": 2.8920993835053443}, ".@JohnCornyn &amp; I wrote a bipartisan bill removing obstacles that delay servicemembers' commercial drivers\u2019 licenses. https://t.co/Ik99SrJbSS": {"sentiment_analysis_weight": {"neg": 0.259, "neu": 0.741, "pos": 0.0, "compound": -0.5994}, "1_gram": 7.243618030818395, "2_gram": 12.487236061636793, "3_gram": 17.728943776871297, "4_gram": 22.968348192066117}, "Veterans who have the training &amp; experience to operate trucks &amp; buses in combat zones have the skills to drive trucks on our highways.": {"sentiment_analysis_weight": {"neg": 0.094, "neu": 0.906, "pos": 0.0, "compound": -0.34}, "1_gram": 5.354511523685461, "2_gram": 9.676764982854788, "3_gram": 13.992564619780822, "4_gram": 18.30307511313482}, "@Equifax @gao @FTC @CFPB @USGAO We're fighting to hold @Equifax accountable. In the meantime, the @CFPB has a helpf\u2026 https://t.co/B78p2wCPos": {"sentiment_analysis_weight": {"neg": 0.106, "neu": 0.894, "pos": 0.0, "compound": -0.3612}, "1_gram": 5.022445989945283, "2_gram": 9.02050173598813, "3_gram": 12.518160025751168, "4_gram": 15.515464333213323}, "I sent letters to @Equifax, the other credit reporting agencies, regulators, &amp; @GAO to figure out how we can reform\u2026 https://t.co/LJXjZNW8n8": {"sentiment_analysis_weight": {"neg": 0.0, "neu": 0.89, "pos": 0.11, "compound": 0.3818}, "1_gram": 3.260792353907776, "2_gram": 5.519635390076761, "3_gram": 7.706652398537366, "4_gram": 9.750458281839947}, "On top of these bills, I launched an investigation into the @Equifax breach &amp; credit reporting industry in general. https://t.co/VLssJGpmC6": {"sentiment_analysis_weight": {"neg": 0.0, "neu": 0.753, "pos": 0.247, "compound": 0.5994}, "1_gram": 3.0141381018981246, "2_gram": 5.026818477848726, "3_gram": 6.99364685206497, "4_gram": 8.959309555668643}, "Bad credit doesn\u2019t make you a bad employee. Workers should compete on the merits, not on their credit scores.": {"sentiment_analysis_weight": {"neg": 0.251, "neu": 0.466, "pos": 0.283, "compound": -0.0258}, "1_gram": 3.0746045503113777, "2_gram": 5.0992091006227565, "3_gram": 6.998813650934134, "4_gram": 8.855498811267298}, "Credit reports are already riddled with errors. The @Equifax hack will make it worse. Inaccurate reports shouldn't hurt your job chances.": {"sentiment_analysis_weight": {"neg": 0.304, "neu": 0.546, "pos": 0.15, "compound": -0.6705}, "1_gram": 4.4976424268737665, "2_gram": 7.93278485374753, "3_gram": 11.221650684876616, "4_gram": 14.502194892274243}, "I also reintroduced the Equal Employment for All Act to prevent employers from asking job applicants for their cred\u2026 https://t.co/FoZQq1lZcU": {"sentiment_analysis_weight": {"neg": 0.0, "neu": 0.948, "pos": 0.052, "compound": 0.0258}, "1_gram": 4.9813979933761985, "2_gram": 8.960846669013605, "3_gram": 12.899897888371202, "4_gram": 15.838595125427913}, "The idea behind our bill is simple: @Equifax doesn't pay you when they sell your data. You shouldn't have to pay them to stop selling it.": {"sentiment_analysis_weight": {"neg": 0.179, "neu": 0.821, "pos": 0.0, "compound": -0.4588}, "1_gram": 1.30300571922472, "2_gram": 2.6037327281828984, "3_gram": 3.499697832379172, "4_gram": 4.179789920702429}, "The FREE Act lets you freeze \u2013 and unfreeze \u2013 access to your credit file at no cost. It's like a free Do Not Call list for your credit data.": {"sentiment_analysis_weight": {"neg": 0.058, "neu": 0.531, "pos": 0.411, "compound": 0.9062}, "1_gram": 4.021509598996235, "2_gram": 7.992659873522474, "3_gram": 11.87189838334283, "4_gram": 15.734802847071478}, "Companies like @Equifax make billions selling access to your data without your consent, then charge you if you want to stop them. It's nuts.": {"sentiment_analysis_weight": {"neg": 0.213, "neu": 0.656, "pos": 0.131, "compound": -0.3326}, "1_gram": 2.396471063804853, "2_gram": 3.730442127609706, "3_gram": 5.051030421007281, "4_gram": 6.3453090847058675}, "I introduced the Freedom from Equifax Exploitation (FREE) Act with @brianschatz. Our bill gives you more control of\u2026 https://t.co/fTz2JkGAPd": {"sentiment_analysis_weight": {"neg": 0.0, "neu": 0.706, "pos": 0.294, "compound": 0.8176}, "1_gram": 2.701002144759204, "2_gram": 4.400054971779615, "3_gram": 6.015377009186883, "4_gram": 7.629985739823273}, "Lot of people are outraged about the @Equifax data breach. I am too. Here\u2019s what I\u2019ve been doing about it this week.": {"sentiment_analysis_weight": {"neg": 0.149, "neu": 0.851, "pos": 0.0, "compound": -0.5423}, "1_gram": 0.6402629167793439, "2_gram": 1.1498068793103224, "3_gram": 1.6563461710734713, "4_gram": 2.15669257276657}, "Today I told an @AnthemInc VP: If they want to make huge profits off taxpayers, they ought to provide decent covera\u2026 https://t.co/YvDICzsWuh": {"sentiment_analysis_weight": {"neg": 0.0, "neu": 0.755, "pos": 0.245, "compound": 0.6705}, "1_gram": 3.8621860092974147, "2_gram": 6.719805808549166, "3_gram": 9.575078833782323, "4_gram": 12.329997876714588}, "More than half of @AnthemInc's revenue comes from programs like Medicare &amp; Medicaid. But they're abandoning people in ACA exchanges.": {"sentiment_analysis_weight": {"neg": 0.141, "neu": 0.787, "pos": 0.072, "compound": -0.3919}, "1_gram": 1.8411981930263843, "2_gram": 3.1774944252684536, "3_gram": 4.470653402608564, "4_gram": 5.637913099373132}, "Insurance giant @AnthemInc sent Congress a ransom note: bigger tax cuts, or they\u2019d pull out of more state health care exchanges.": {"sentiment_analysis_weight": {"neg": 0.093, "neu": 0.761, "pos": 0.146, "compound": 0.3102}, "1_gram": 3.197027340383414, "2_gram": 5.858340395052544, "3_gram": 8.265107995176216, "4_gram": 10.524187534568348}, "When the GOP tried to repeal the ACA, some \u2013 like @BCBSMA \u2013 fought for their customers. But not @AnthemInc.": {"sentiment_analysis_weight": {"neg": 0.085, "neu": 0.825, "pos": 0.09, "compound": 0.0258}, "1_gram": 2.487624218517778, "2_gram": 4.82089704130485, "3_gram": 7.149405253278313, "4_gram": 9.458485312759107}, "Undermining the INF Treaty is grossly irresponsible. Heading to the floor now to discuss my NDAA amendment. Watch: https://t.co/jc1R7Es8hG": {"sentiment_analysis_weight": {"neg": 0.289, "neu": 0.711, "pos": 0.0, "compound": -0.743}, "1_gram": 5.022865068764774, "2_gram": 9.34573013752955, "3_gram": 13.667838425544518, "4_gram": 16.98959273125862}, "Today I stood with @SenSanders to support his Medicare for All bill. Health care is a basic human right &amp; we fight\u2026 https://t.co/LfM2m7wjOu": {"sentiment_analysis_weight": {"neg": 0.091, "neu": 0.702, "pos": 0.207, "compound": 0.5106}, "1_gram": 1.380096868903132, "2_gram": 1.7556275277606015, "3_gram": 2.128811412599471, "4_gram": 2.3905302040263443}, "@USChamber The companies paying for a @USChamber membership \u2013 they\u2019re being taken for a ride.": {"sentiment_analysis_weight": {"neg": 0.0, "neu": 1.0, "pos": 0.0, "compound": 0.0}, "1_gram": 2.0241608518644476, "2_gram": 3.381655037062228, "3_gram": 4.737712311583118, "4_gram": 6.030305265949716}, ".@USChamber sucks billions of dollars from member companies \u2013 so it\u2019ll pick a losing fight if it has to, as long as the money keeps flowing.": {"sentiment_analysis_weight": {"neg": 0.259, "neu": 0.741, "pos": 0.0, "compound": -0.7717}, "1_gram": 3.1220731223915066, "2_gram": 5.410812911449674, "3_gram": 6.6226296235847695, "4_gram": 7.6733352246087545}, "The fiduciary rule is working for consumers, start-ups and big investment companies. So why is the Chamber of Comme\u2026 https://t.co/6iYRjUH61U": {"sentiment_analysis_weight": {"neg": 0.0, "neu": 1.0, "pos": 0.0, "compound": 0.0}, "1_gram": 4.736795166509362, "2_gram": 8.473231008548726, "3_gram": 11.20926939430829, "4_gram": 13.878287131100302}, "@RandPaul It\u2019s long past time for Congress to do right by our troops &amp; the American people, which is why I\u2019m suppor\u2026 https://t.co/20zdhE6ger": {"sentiment_analysis_weight": {"neg": 0.0, "neu": 1.0, "pos": 0.0, "compound": 0.0}, "1_gram": 1.7732865344592839, "2_gram": 2.5311884535339524, "3_gram": 3.2867735305322667, "4_gram": 4.040816976773639}, ".@RandPaul is fighting for an amendment to the annual defense bill that would repeal the AUMF &amp; give Congress six months to replace it.": {"sentiment_analysis_weight": {"neg": 0.096, "neu": 0.846, "pos": 0.058, "compound": -0.25}, "1_gram": 0.9656515188764988, "2_gram": 1.913999036571837, "3_gram": 2.7360595529801746, "4_gram": 3.534441779727376}, "It\u2019s been 16 yrs since Congress passed the existing AUMF after 9/11, but yr after yr, Congress refuses to re-examine this outdated policy.": {"sentiment_analysis_weight": {"neg": 0.0, "neu": 1.0, "pos": 0.0, "compound": 0.0}, "1_gram": 2.162936770715992, "2_gram": 4.290620822302106, "3_gram": 6.083783892098829, "4_gram": 7.861596084702572}, "Congress owes our troops &amp; their families a full debate to authorize the use of military force before we send them into harm\u2019s way.": {"sentiment_analysis_weight": {"neg": 0.137, "neu": 0.863, "pos": 0.0, "compound": -0.5423}, "1_gram": 2.2158449873587664, "2_gram": 4.401981121479265, "3_gram": 5.586929607143708, "4_gram": 6.519928775069359}, "RT @MassAGO: Edie\u2019s life was a testament to the power of small acts of courage. She will be missed, but will never be forgotten. https://t.\u2026": {"sentiment_analysis_weight": {"neg": 0.06, "neu": 0.787, "pos": 0.154, "compound": 0.3609}, "1_gram": 2.300960727637819, "2_gram": 4.600375577861523, "3_gram": 6.399406550925917, "4_gram": 7.698437523990309}, "Read my @BostonGlobe op-ed on why we must give opioid addiction treatment providers the support they need. https://t.co/HVdk8y0KCJ": {"sentiment_analysis_weight": {"neg": 0.0, "neu": 0.881, "pos": 0.119, "compound": 0.4019}, "1_gram": 2.861925070548441, "2_gram": 4.706900988554509, "3_gram": 6.547312783614101, "4_gram": 7.387370596372809}, "I met with MA opioid addiction treatment providers who give affordable, innovative care \u2013 but they\u2019re stretched too\u2026 https://t.co/xPOipAwNsl": {"sentiment_analysis_weight": {"neg": 0.0, "neu": 0.816, "pos": 0.184, "compound": 0.4678}, "1_gram": 3.440007010920049, "2_gram": 5.878064704101305, "3_gram": 8.244296369574183, "4_gram": 10.607648800220929}, "The opioid epidemic hits all of MA, so we surveyed health providers about how we can improve &amp; expand their work. https://t.co/HqWGUwd0EW": {"sentiment_analysis_weight": {"neg": 0.0, "neu": 0.809, "pos": 0.191, "compound": 0.6369}, "1_gram": 3.2995421955127764, "2_gram": 5.5987250665555575, "3_gram": 7.806601390409437, "4_gram": 9.680790398629098}, "To everyone who wrote emails, tweeted, and showed up: Thank you! You saved health care in America. Keep it up, we n\u2026 https://t.co/FdXsasmO6U": {"sentiment_analysis_weight": {"neg": 0.0, "neu": 0.712, "pos": 0.288, "compound": 0.8176}, "1_gram": 3.0640648117345615, "2_gram": 5.127707147761473, "3_gram": 7.167142503699058, "4_gram": 9.201719372831255}, "RT @NWSMiami: 9/10 820 PM Stay in safe shelter, we are still experiencing damaging wind gust across South Florida #FLwx": {"sentiment_analysis_weight": {"neg": 0.136, "neu": 0.744, "pos": 0.12, "compound": -0.1027}, "1_gram": 6.145352831461239, "2_gram": 11.289513767809247, "3_gram": 15.409284460254817, "4_gram": 19.40777855695572}, "RT @FLSERT: Do not go outside, even if the storm appears to have subsided #FLPrepares": {"sentiment_analysis_weight": {"neg": 0.0, "neu": 1.0, "pos": 0.0, "compound": 0.0}, "1_gram": 3.4521883015310264, "2_gram": 5.9031847079488236, "3_gram": 6.854181114366619, "4_gram": 7.793012769826561}, "RT @FLSERT: The #FL Emergency Information Line has been activated 24/7. For up-to-date information regarding #Irma please call 1-800-342-35\u2026": {"sentiment_analysis_weight": {"neg": 0.1, "neu": 0.811, "pos": 0.089, "compound": -0.0772}, "1_gram": 4.859001497854424, "2_gram": 9.591811100595622, "3_gram": 12.82462070333681, "4_gram": 15.914213838750863}, "Equifax proves why we must protect your right to join class actions. https://t.co/Z2APQcRb0K": {"sentiment_analysis_weight": {"neg": 0.0, "neu": 0.73, "pos": 0.27, "compound": 0.5859}, "1_gram": 1.7441936451185798, "2_gram": 2.4639970463347205, "3_gram": 2.683402991271052, "4_gram": 2.887749071553557}, "Keep fighting, @RepJayapal! #NeverthelessShePersisted https://t.co/QssQq3hWpk": {"sentiment_analysis_weight": {"neg": 0.294, "neu": 0.706, "pos": 0.0, "compound": -0.3612}, "1_gram": 2.3720101773125393, "2_gram": 3.729734640339364, "3_gram": 5.06380583313289, "4_gram": 6.064189710292199}, "RT @MassNurses: MNA Western Mass nurses with @SenWarren at the Pioneer Valley Central Labor Council breakfast this morning https://t.co/svC\u2026": {"sentiment_analysis_weight": {"neg": 0.0, "neu": 1.0, "pos": 0.0, "compound": 0.0}, "1_gram": 6.3720489663356785, "2_gram": 11.74290603755813, "3_gram": 16.113365652500775, "4_gram": 19.483471285142524}, "Happy to keep the Labor Day celebrations going with the Pioneer Valley CLC today! https://t.co/fAASUbmBtP": {"sentiment_analysis_weight": {"neg": 0.0, "neu": 0.812, "pos": 0.188, "compound": 0.5719}, "1_gram": 3.8883858391125243, "2_gram": 6.753515864271559, "3_gram": 9.617825957443142, "4_gram": 12.46749635402812}, ".@wesoldieron is an incredible organization fighting to end veteran homelessness. Very glad to visit their women's\u2026 https://t.co/wCMsop3n0U": {"sentiment_analysis_weight": {"neg": 0.11, "neu": 0.746, "pos": 0.144, "compound": 0.2006}, "1_gram": 3.6989942436897634, "2_gram": 5.397988487379525, "3_gram": 7.095298273502479, "4_gram": 8.785451356236113}, "The @CFPB's new rule would stop companies like @Equifax from avoiding legal accountability like this -- as long as @GOP doesn't reverse it.": {"sentiment_analysis_weight": {"neg": 0.164, "neu": 0.605, "pos": 0.231, "compound": 0.2263}, "1_gram": 1.6311292563206554, "2_gram": 3.2599798023747693, "3_gram": 4.444385903984437, "4_gram": 5.62725037483716}, "That's right: @Equifax fails to protect your data and then they demand you give up legal rights if you want to limit the damage they caused.": {"sentiment_analysis_weight": {"neg": 0.228, "neu": 0.608, "pos": 0.164, "compound": -0.4767}, "1_gram": 1.6199442667503126, "2_gram": 2.903738298758841, "3_gram": 4.180597555874533, "4_gram": 5.364689517392737}, ".@Equifax is forcing you to give up your right to join a class action against the company if you want their credit\u2026 https://t.co/uiJcFXe38d": {"sentiment_analysis_weight": {"neg": 0.0, "neu": 0.775, "pos": 0.225, "compound": 0.6249}, "1_gram": 1.6096320394099353, "2_gram": 2.1948738349174324, "3_gram": 2.7784311728581175, "4_gram": 3.161634528497919}, "The @Equifax breach is Exhibit A for why we must stop @GOP from reversing the @CFPB's rule protecting your right to join class actions.": {"sentiment_analysis_weight": {"neg": 0.087, "neu": 0.827, "pos": 0.087, "compound": 0.0}, "1_gram": 1.982017927418092, "2_gram": 3.838676530366188, "3_gram": 5.650111556078507, "4_gram": 7.360031430275678}, "It's also outrageous that @Equifax waited so long to disclose the breach -- needlessly leaving nearly half of America at risk for a month.": {"sentiment_analysis_weight": {"neg": 0.203, "neu": 0.797, "pos": 0.0, "compound": -0.6249}, "1_gram": 3.4141399609770597, "2_gram": 6.759693869490907, "3_gram": 10.102982543341797, "4_gram": 13.40530689703841}, "It's outrageous that @Equifax -- a company whose one job is to collect consumer information -- failed to safeguard data for 143M Americans.": {"sentiment_analysis_weight": {"neg": 0.243, "neu": 0.656, "pos": 0.1, "compound": -0.5719}, "1_gram": 4.183516193157698, "2_gram": 8.35861949402534, "3_gram": 11.53253514643693, "4_gram": 14.538819812027556}, "I'm glad community bankers agree: @WellsFargo's Board should be removed. Government must hold big banks accountable. https://t.co/hPb8mAaNF4": {"sentiment_analysis_weight": {"neg": 0.0, "neu": 0.744, "pos": 0.256, "compound": 0.6705}, "1_gram": 2.8810324896735753, "2_gram": 4.76011566160836, "3_gram": 6.628048689091293, "4_gram": 8.448008686654294}, "Debt-free college for low-income Boston U students leads to a boost in their enrollment! Way to go @BU_Tweets! https://t.co/lHJZcqtzCe": {"sentiment_analysis_weight": {"neg": 0.167, "neu": 0.616, "pos": 0.217, "compound": 0.34}, "1_gram": 3.0658638613579607, "2_gram": 5.065061056049254, "3_gram": 7.034449029754856, "4_gram": 8.920149687826243}, "About to speak on the Senate floor about why we must #DefendDACA and pass the Dream Act now. Watch: https://t.co/jc1R7Es8hG": {"sentiment_analysis_weight": {"neg": 0.0, "neu": 0.913, "pos": 0.087, "compound": 0.25}, "1_gram": 0.5234785381499456, "2_gram": 0.842683572026387, "3_gram": 1.1610686739153724, "4_gram": 1.4513220157256945}, "Thank you, @MassAGO Healey, for fighting for Dreamers in MA &amp; across this country. #DefendDACA https://t.co/1OeWJUj7NQ": {"sentiment_analysis_weight": {"neg": 0.119, "neu": 0.762, "pos": 0.119, "compound": 0.0}, "1_gram": 2.8695739861277745, "2_gram": 4.73157221467979, "3_gram": 6.590895082623979, "4_gram": 7.949863968267284}, "The fight over @CFPB\u2019s arbitration rule is about whose side you stand on: big Wall St banks or military families. https://t.co/3fhi2b8osa": {"sentiment_analysis_weight": {"neg": 0.106, "neu": 0.894, "pos": 0.0, "compound": -0.3818}, "1_gram": 3.0193819570981213, "2_gram": 5.0384045897262455, "3_gram": 7.045265060192205, "4_gram": 9.038072918220298}, "I agree, President Obama. https://t.co/A7oRZq5JeH": {"sentiment_analysis_weight": {"neg": 0.0, "neu": 0.667, "pos": 0.333, "compound": 0.3612}, "1_gram": 1.0746136491254572, "2_gram": 1.1472779805121232, "3_gram": 1.1825078185819429, "4_gram": 1.2056189684685246}, "We cannot sit back while our family, friends &amp; neighbors are driven out of their homes. We must fight to protect Dreamers &amp; #DefendDACA.": {"sentiment_analysis_weight": {"neg": 0.089, "neu": 0.717, "pos": 0.195, "compound": 0.4767}, "1_gram": 1.305403045028058, "2_gram": 2.5183702815897737, "3_gram": 3.7102168157101487, "4_gram": 4.805984918457974}, "America should keep its promises. If @realDonaldTrump doesn\u2019t know that, then Congress must act to make DACA permanent. #DefendDACA": {"sentiment_analysis_weight": {"neg": 0.0, "neu": 0.874, "pos": 0.126, "compound": 0.3818}, "1_gram": 1.023930080124326, "2_gram": 1.9481015118174367, "3_gram": 2.6975417607148477, "4_gram": 3.387241749872}, "Turning our backs on Dreamers makes us weaker, makes us less safe, &amp; betrays our values. #DefendDACA": {"sentiment_analysis_weight": {"neg": 0.298, "neu": 0.487, "pos": 0.215, "compound": -0.2568}, "1_gram": 2.3668827366250587, "2_gram": 4.392856382341026, "3_gram": 6.3454521388896294, "4_gram": 8.129431911032777}, "Subjecting Dreamers to mass deportation is part of the bigoted policies that are a cornerstone of @realDonaldTrump\u2019s admin. #DefendDACA": {"sentiment_analysis_weight": {"neg": 0.0, "neu": 1.0, "pos": 0.0, "compound": 0.0}, "1_gram": 3.7740158046950327, "2_gram": 6.457122518480978, "3_gram": 9.069150800894368, "4_gram": 11.679568959144058}, "Very proud of the @MMAAdmissions &amp; their officers for stepping up to help our friends &amp; family in the Gulf Coast. https://t.co/Ihw3jCxGrD": {"sentiment_analysis_weight": {"neg": 0.0, "neu": 0.696, "pos": 0.304, "compound": 0.8479}, "1_gram": 3.1281789882284814, "2_gram": 5.233102162503474, "3_gram": 7.324969652650555, "4_gram": 9.41567147218507}, "Read my office\u2019s new #LaborDay report on how @realDonaldTrump has betrayed America\u2019s working men &amp; women. https://t.co/9I1Kom4XD2": {"sentiment_analysis_weight": {"neg": 0.182, "neu": 0.818, "pos": 0.0, "compound": -0.6124}, "1_gram": 2.3005333114290876, "2_gram": 3.584117470315802, "3_gram": 4.863137506256042, "4_gram": 6.104766522858358}, "And Trump has proposed huge cuts to @USDOL\u2019s budget \u2013 damaging its ability to enforce labor laws &amp; protect/support workers. #LaborDay": {"sentiment_analysis_weight": {"neg": 0.181, "neu": 0.493, "pos": 0.326, "compound": 0.5267}, "1_gram": 2.316224807430039, "2_gram": 4.554653937587959, "3_gram": 6.759520093006434, "4_gram": 8.94305536457106}, "Trump has delayed/weakened basic worker protections: overtime, beryllium &amp; silica exposure, mine safety, EEOC data, &amp; more. #LaborDay": {"sentiment_analysis_weight": {"neg": 0.183, "neu": 0.696, "pos": 0.122, "compound": -0.1027}, "1_gram": 6.770656890363381, "2_gram": 13.457854756091272, "3_gram": 20.132904284223244, "4_gram": 26.306440953051133}, "Trump\u2019s nominees for @USDOL &amp; @NLRB have a history of turning their backs on working people. #LaborDay": {"sentiment_analysis_weight": {"neg": 0.074, "neu": 0.926, "pos": 0.0, "compound": -0.0516}, "1_gram": 1.7439986948151585, "2_gram": 3.404538364994821, "3_gram": 5.0596168824449235, "4_gram": 6.537276045056318}, ".@realDonaldTrump's record is clear: over and over, he\u2019s delivered one sucker punch after another to America's workers. #LaborDay": {"sentiment_analysis_weight": {"neg": 0.155, "neu": 0.727, "pos": 0.118, "compound": -0.2023}, "1_gram": 2.4836455359131637, "2_gram": 4.872510852046106, "3_gram": 7.233161492695965, "4_gram": 9.515701407966686}, "Happy #LaborDay! Today we say loud &amp; clear: Unions built America's middle class, &amp; unions will rebuild America's mi\u2026 https://t.co/1YWVEmZYNC": {"sentiment_analysis_weight": {"neg": 0.0, "neu": 0.76, "pos": 0.24, "compound": 0.743}, "1_gram": 2.5333689439807534, "2_gram": 4.043482074008018, "3_gram": 5.476274670832396, "4_gram": 6.904147075310227}, "Glad to start this #LaborDay in Worcester the 46th annual Central @MassAFLCIO Labor Day breakfast! https://t.co/IYD2pAkFTV": {"sentiment_analysis_weight": {"neg": 0.0, "neu": 0.85, "pos": 0.15, "compound": 0.4588}, "1_gram": 4.209916800295104, "2_gram": 7.3722145529711565, "3_gram": 10.533692373659763, "4_gram": 13.644816212047479}, "RT @marty_walsh: Truck #8 just got to City Hall and is starting to get packed up! 26 more tons of supplies to Houston -- thank you Boston.\u2026": {"sentiment_analysis_weight": {"neg": 0.0, "neu": 0.906, "pos": 0.094, "compound": 0.3612}, "1_gram": 3.336412060490605, "2_gram": 6.560521114756868, "3_gram": 9.532352264695112, "4_gram": 11.996607657057602}, "RT @marty_walsh: To Houston,\n7 trucks. \n280 tons of supplies. \nHundreds of volunteers. \nInfinite number of donations, prayers &amp; well wishes\u2026": {"sentiment_analysis_weight": {"neg": 0.0, "neu": 0.773, "pos": 0.227, "compound": 0.4588}, "1_gram": 4.519833485339281, "2_gram": 8.705141742231998, "3_gram": 12.608191934608584, "4_gram": 16.50930679197345}, "@BetsyDeVosED @usedgov Is @BetsyDeVosED trolling us with this DeVry hire? It's astounding, &amp; it\u2019s exactly why I lau\u2026 https://t.co/QZUM4uafCB": {"sentiment_analysis_weight": {"neg": 0.0, "neu": 0.872, "pos": 0.128, "compound": 0.4215}, "1_gram": 4.955182353569093, "2_gram": 8.82703137380485, "3_gram": 12.448482937760804, "4_gram": 16.06829351812887}, "@BetsyDeVosED @usedgov .@usedgov\u2019s student aid enforcement office was literally created in response to DeVry &amp; othe\u2026 https://t.co/lJD28F0itc": {"sentiment_analysis_weight": {"neg": 0.0, "neu": 0.9, "pos": 0.1, "compound": 0.25}, "1_gram": 4.873178034395965, "2_gram": 8.663022735458593, "3_gram": 12.202469980241418, "4_gram": 15.491563242723359}, ".@BetsyDeVosED hired a former DeVry official to be the cop in charge of policing sham colleges at @usedgov. https://t.co/Irw7VzOyr1": {"sentiment_analysis_weight": {"neg": 0.0, "neu": 1.0, "pos": 0.0, "compound": 0.0}, "1_gram": 5.6891542318622985, "2_gram": 10.294975130391265, "3_gram": 13.90039857264042, "4_gram": 17.504390446381798}, "Opioid treatment centers like High Point rely on Medicaid. Recent threats put their patients at risk. We need to expand \u2013 not cut \u2013 funding.": {"sentiment_analysis_weight": {"neg": 0.166, "neu": 0.61, "pos": 0.224, "compound": 0.1813}, "1_gram": 1.6479155988814926, "2_gram": 3.1460985774421295, "3_gram": 4.520948222669432, "4_gram": 5.766392581553124}, "Last wk, I visited the High Point Treatment Center in Plymouth, a treatment facility on the front lines of the opio\u2026 https://t.co/ugYQhBxxpt": {"sentiment_analysis_weight": {"neg": 0.0, "neu": 1.0, "pos": 0.0, "compound": 0.0}, "1_gram": 5.109285089174071, "2_gram": 9.202176735725192, "3_gram": 12.794670925996508, "4_gram": 16.384861816228145}, "More than 2000 people died of opioid overdoses in Massachusetts last year. It's an epidemic \u2013 and it's heartbreaking. #EndOverdose": {"sentiment_analysis_weight": {"neg": 0.28, "neu": 0.72, "pos": 0.0, "compound": -0.765}, "1_gram": 4.118397430503546, "2_gram": 7.2318929002227765, "3_gram": 9.835584448373378, "4_gram": 11.938088348067938}, "To every DREAMer in this country: You are an American. This country is your home. And we\u2019re fighting for you. #saveDACA": {"sentiment_analysis_weight": {"neg": 0.106, "neu": 0.894, "pos": 0.0, "compound": -0.3612}, "1_gram": 1.1285588321738493, "2_gram": 1.756695188640053, "3_gram": 2.3693957460413957, "4_gram": 2.481131983288447}, "Ending DACA would tear apart families &amp; rip young people away from the only country they\u2019ve ever known. #saveDACA": {"sentiment_analysis_weight": {"neg": 0.0, "neu": 1.0, "pos": 0.0, "compound": 0.0}, "1_gram": 1.8928435296229948, "2_gram": 3.185687059245989, "3_gram": 4.233076043414437, "4_gram": 5.227895857622413}, "I'm proud of all the men &amp; women in uniform from Massachusetts who are helping with efforts in Houston. https://t.co/BMccQFvqlQ": {"sentiment_analysis_weight": {"neg": 0.0, "neu": 0.782, "pos": 0.218, "compound": 0.6486}, "1_gram": 1.9988611538466, "2_gram": 2.9957729899544083, "3_gram": 3.9815346816103654, "4_gram": 4.954284163117336}, "Congress also can't look the other way. We need the @WellsFargo hearing Dems called for earlier this month. https://t.co/hkgsDJt8V4": {"sentiment_analysis_weight": {"neg": 0.0, "neu": 1.0, "pos": 0.0, "compound": 0.0}, "1_gram": 1.6912585693424909, "2_gram": 2.372416128583972, "3_gram": 3.0131762315456445, "4_gram": 3.6482060081204106}, "The @federalreserve should remove every @wellsfargo Board member who served during this scandal. I don't know what they're waiting for.": {"sentiment_analysis_weight": {"neg": 0.151, "neu": 0.849, "pos": 0.0, "compound": -0.5228}, "1_gram": 2.1443347580746894, "2_gram": 4.28734587152509, "3_gram": 5.31924587386438, "4_gram": 6.333277438506011}, "Unbelievable. @WellsFargo's massive fraud is even worse than we thought. https://t.co/eVJgAgNR0i": {"sentiment_analysis_weight": {"neg": 0.369, "neu": 0.535, "pos": 0.096, "compound": -0.7269}, "1_gram": 2.5697958800524514, "2_gram": 3.1395917601049033, "3_gram": 3.6501666544657807, "4_gram": 4.159199918069716}, "Think tanks play a critical role in shaping policy, but their credibility is jeopardized when decisions are based on funder preferences.": {"sentiment_analysis_weight": {"neg": 0.077, "neu": 0.843, "pos": 0.08, "compound": 0.0129}, "1_gram": 5.567095913482164, "2_gram": 10.588737281509779, "3_gram": 14.277045316204063, "4_gram": 17.71389562495083}, "This story is troubling. https://t.co/UmRVi2UnSI": {"sentiment_analysis_weight": {"neg": 0.368, "neu": 0.632, "pos": 0.0, "compound": -0.5423}, "1_gram": 1.5546152994831448, "2_gram": 2.107037616510149, "3_gram": 2.6090624772573445, "4_gram": 3.1094463544166535}, "RT @CFPB: If you have been affected by Hurricane #Harvey, we have resources to help you protect and rebuild your finances. https://t.co/Bdh\u2026": {"sentiment_analysis_weight": {"neg": 0.057, "neu": 0.753, "pos": 0.19, "compound": 0.5719}, "1_gram": 1.778458190187878, "2_gram": 2.555724485262526, "3_gram": 3.2214822129462544, "4_gram": 3.8794785509216894}, "RT @HCSOTexas: IMPORTANT: If rescued, REMOVE white towel/sheet before leaving. Rescue time wasted on empty homes, while others still wait.\u2026": {"sentiment_analysis_weight": {"neg": 0.173, "neu": 0.554, "pos": 0.273, "compound": 0.4404}, "1_gram": 5.822635349270165, "2_gram": 11.477412136760432, "3_gram": 16.1071889242507, "4_gram": 20.622382378407632}, "The people of the Gulf Coast desperately need our help. MA will keep doing everything we can to come to their aid. https://t.co/NdyVVTqp0T": {"sentiment_analysis_weight": {"neg": 0.092, "neu": 0.813, "pos": 0.095, "compound": 0.0258}, "1_gram": 2.1704987390660175, "2_gram": 3.340638153662037, "3_gram": 4.506106607704744, "4_gram": 5.670409391134881}, "And I\u2019m glad that Boston Mayor @Marty_Walsh is sending high-water rescue vehicles &amp; cots to help the people of Houston.": {"sentiment_analysis_weight": {"neg": 0.0, "neu": 0.654, "pos": 0.346, "compound": 0.8402}, "1_gram": 3.0087999185944487, "2_gram": 5.816727236839857, "3_gram": 8.621893549034787, "4_gram": 11.412033668784163}, "I\u2019m also glad that two Coast Guard helicopters, a plane, &amp; crew from Cape Cod are already helping with Hurricane #Harvey rescue efforts.": {"sentiment_analysis_weight": {"neg": 0.0, "neu": 0.679, "pos": 0.321, "compound": 0.8176}, "1_gram": 4.277019370314573, "2_gram": 8.522677658184469, "3_gram": 12.65758325788233, "4_gram": 16.723077092874327}, "I\u2019m proud &amp; grateful for the FEMA volunteers based in Beverly, MA who are on their way to assist the Gulf Coast. https://t.co/nCwHD4MQBd": {"sentiment_analysis_weight": {"neg": 0.0, "neu": 0.783, "pos": 0.217, "compound": 0.7269}, "1_gram": 3.1370687353141262, "2_gram": 5.27218815288946, "3_gram": 7.396157426012944, "4_gram": 9.507114488987446}}